ez_setup.py
setup.py
test_wsgiakismet.py
wsgiakismet.py
tests/test_wsgiakismet.py
wsgiakismet.egg-info/PKG-INFO
wsgiakismet.egg-info/SOURCES.txt
wsgiakismet.egg-info/dependency_links.txt
wsgiakismet.egg-info/top_level.txt
wsgiakismet.egg-info/zip-safe
