Metadata-Version: 1.0
Name: wsgiakismet
Version: 0.1
Summary: Akismet SPAM blocking WSGI middleware.
Home-page: UNKNOWN
Author: L. C. Rees
Author-email: lcrees@gmail.com
License: BSD
Keywords: WSGI comment spam blocking blog middleware web HTTP
Platform: UNKNOWN
Classifier: Development Status :: 4 - Beta
Classifier: Environment :: Web Environment
Classifier: License :: OSI Approved :: BSD License
Classifier: Natural Language :: English
Classifier: Operating System :: OS Independent
Classifier: Programming Language :: Python
Classifier: Topic :: Internet :: WWW/HTTP :: WSGI :: Middleware
